LICENSE
MANIFEST.in
README.rst
gmute.py
setup.py
gmute.egg-info/PKG-INFO
gmute.egg-info/SOURCES.txt
gmute.egg-info/dependency_links.txt
gmute.egg-info/entry_points.txt
gmute.egg-info/top_level.txt