Metadata-Version: 1.2
Name: gmute
Version: 1.2.0
Summary: Gmail mute support for mutt and other email clients
Home-page: https://github.com/cdown/gmute
Author: Chris Down
Author-email: chris@chrisdown.name
License: MIT
Keywords: email gmail mutt headers mute productivity
Platform: UNKNOWN
Classifier: Development Status :: 4 - Beta
Classifier: License :: OSI Approved :: MIT License
Classifier: Operating System :: POSIX :: Linux
Classifier: Programming Language :: Python :: 3
Classifier: Programming Language :: Python :: 3.5
Classifier: Programming Language :: Python :: 3.6
Classifier: Programming Language :: Python :: 3.7
Classifier: Topic :: Communications :: Email
Classifier: Topic :: Utilities
Requires-Python: >=3.5
